{"tech":[{"titre":"Actus tech ? venir","description":"Reessayez dans quelques minutes.","lien":"#","image":"","date":"2026-06-14T16:49:33.757Z","source":"Trinite"}],"mode":[{"titre":"Actus mode ? venir","description":"Reessayez dans quelques minutes.","lien":"#","image":"","date":"2026-06-14T16:49:33.758Z","source":"Trinite"}],"sport":[{"titre":"Actus sport ? venir","description":"Reessayez dans quelques minutes.","lien":"#","image":"","date":"2026-06-14T16:49:33.758Z","source":"Trinite"}],"derniereMiseAJour":"2026-06-14T16:49:23.814Z"}