{"tech":[{"titre":"Actus tech ? venir","description":"Reessayez dans quelques minutes.","lien":"#","image":"","date":"2026-06-30T02:19:33.045Z","source":"Trinite"}],"mode":[{"titre":"Actus mode ? venir","description":"Reessayez dans quelques minutes.","lien":"#","image":"","date":"2026-06-30T02:19:33.045Z","source":"Trinite"}],"sport":[{"titre":"Actus sport ? venir","description":"Reessayez dans quelques minutes.","lien":"#","image":"","date":"2026-06-30T02:19:33.045Z","source":"Trinite"}],"derniereMiseAJour":"2026-06-30T02:19:23.347Z"}